sentry_mattermost/__init__.py
sentry_mattermost/plugin.py
sentry_mattermost_miare-0.0.1.dist-info/LICENSE
sentry_mattermost_miare-0.0.1.dist-info/METADATA
sentry_mattermost_miare-0.0.1.dist-info/WHEEL
sentry_mattermost_miare-0.0.1.dist-info/entry_points.txt
sentry_mattermost_miare-0.0.1.dist-info/top_level.txt
sentry_mattermost_miare-0.0.1.dist-info/RECORD
